tinyadaptparts-stubs/SH1106oled.pyi
tinyadaptparts-stubs/__init__.pyi
tinyadaptparts-stubs/analog.pyi
tinyadaptparts-stubs/button.pyi
tinyadaptparts-stubs/led.pyi
tinyadaptparts_stubs-1.0.1.dist-info/LICENSE
tinyadaptparts_stubs-1.0.1.dist-info/METADATA
tinyadaptparts_stubs-1.0.1.dist-info/WHEEL
tinyadaptparts_stubs-1.0.1.dist-info/RECORD
